minimal_surface.cp312-win_amd64.pyd
minimal_surface-0.0.2.dist-info/LICENSE
minimal_surface-0.0.2.dist-info/METADATA
minimal_surface-0.0.2.dist-info/WHEEL
minimal_surface-0.0.2.dist-info/top_level.txt
minimal_surface-0.0.2.dist-info/RECORD
